{"firstName":"Caner","lastName":"Vural","transcript":[{"TRD121":"F","CSE1200":"BB","PHYS1103":"CC","CSE1241":"AA","PHYS1101":"CC","ATA121":"DD","MBG1201":"F","MATH1001":"DC"},{"PHYS1104":"DC","TRD121":"DC","PHYS1102":"AA","CSE1242":"BB","ATA122":"DC","MBG1201":"CC","MATH1002":"BA","MATH2256":"AA"},{"TRD122":"CC","MATH2055":"CC","NTExxx":"AA","CSE2023":"DC","MATH2059":"CB","EE2031":"CC","CSE2225":"CB"},{},{},{},{},{}],"log":["The advisor didn't allow TRD122 because student failed prereq. TRD121","The advisor didn't approve NTExxx because of total credit","The advisor didn't approve ECON2004 because of total credit"],"student_id":"150122051","studentSemester":3}