{"firstName":"Fadime","lastName":"Selvi","transcript":[{"TRD121":"CC","CSE1200":"CB","PHYS1103":"DC","CSE1241":"BA","PHYS1101":"AA","ATA121":"AA","MBG1201":"AA","MATH1001":"DC"},{"PHYS1104":"AA","TRD122":"DC","PHYS1102":"AA","NTExxx":"CC","CSE1242":"CC","ATA122":"F","MATH1002":"F","MATH2256":"BA"},{"MATH2055":"DC","CSE2023":"DD","ATA122":"F","MATH1002":"AA","MATH2059":"CC","EE2031":"BA"},{},{},{},{},{}],"log":["The advisor didn't approve ECON2004 because of total credit","The advisor didn't approve CSE2225 because of total credit"],"student_id":"150122085","studentSemester":3}