{"firstName":"Metin","lastName":"Yılmaz","transcript":[{"TRD121":"F","CSE1200":"DD","PHYS1103":"DC","CSE1241":"BA","PHYS1101":"AA","ATA121":"BB","MBG1201":"F","MATH1001":"DC"},{"PHYS1104":"DC","TRD121":"DC","PHYS1102":"CB","CSE1242":"BA","ATA122":"DD","MBG1201":"DC","MATH1002":"AA","MATH2256":"AA"},{"TRD122":"BB","MATH2055":"AA","NTExxx":"DD","CSE2023":"DC","MATH2059":"BB","EE2031":"DC","CSE2225":"DD"},{},{},{},{},{}],"log":["The advisor didn't allow TRD122 because student failed prereq. TRD121","The advisor didn't approve NTExxx because of total credit","The advisor didn't approve ECON2004 because of total credit"],"student_id":"150122077","studentSemester":3}